{
  "version": "5.4.1",
  "flags": {},
  "shapes": [
    {
      "label": "scratch",
      "points": [
        [
          2721.0,
          1066.5
        ],
        [
          2700.0,
          1065.5
        ],
        [
          2623.0,
          1033.5
        ],
        [
          2570.0,
          1024.5
        ],
        [
          2558.0,
          1014.5
        ],
        [
          2519.0,
          1008.5
        ],
        [
          2501.0,
          1010.5
        ],
        [
          2487.0,
          1007.5
        ],
        [
          2476.0,
          1008.5
        ],
        [
          2463.0,
          1013.5
        ],
        [
          2436.0,
          1034.5
        ],
        [
          2422.0,
          1037.5
        ],
        [
          2396.0,
          1025.5
        ],
        [
          2382.0,
          1014.5
        ],
        [
          2347.0,
          996.5
        ],
        [
          2326.0,
          995.5
        ],
        [
          2313.5,
          990.0
        ],
        [
          2307.5,
          971.0
        ],
        [
          2305.5,
          917.0
        ],
        [
          2309.5,
          730.0
        ],
        [
          2312.5,
          696.0
        ],
        [
          2326.0,
          668.5
        ],
        [
          2336.0,
          659.5
        ],
        [
          2349.0,
          655.5
        ],
        [
          2389.0,
          658.5
        ],
        [
          2411.0,
          663.5
        ],
        [
          2452.5,
          695.0
        ],
        [
          2451.5,
          703.0
        ],
        [
          2464.0,
          718.5
        ],
        [
          2485.0,
          708.5
        ],
        [
          2517.0,
          705.5
        ],
        [
          2561.0,
          695.5
        ],
        [
          2590.0,
          685.5
        ],
        [
          2626.0,
          686.5
        ],
        [
          2665.0,
          701.5
        ],
        [
          2681.5,
          731.0
        ],
        [
          2688.0,
          735.5
        ],
        [
          2701.0,
          741.5
        ],
        [
          2735.0,
          749.0
        ],
        [
          2735.0,
          1063.0
        ]
      ],
      "group_id": null,
      "description": "",
      "shape_type": "polygon",
      "flags": {},
      "mask": null
    },
    {
      "label": "scratch",
      "points": [
        [
          1762.8775510204082,
          1051.5
        ],
        [
          1687.8775510204082,
          1037.5
        ],
        [
          1631.8775510204082,
          1010.4999999999999
        ],
        [
          1566.8775510204082,
          1005.4999999999999
        ],
        [
          1517.8775510204082,
          1031.5
        ],
        [
          1475.8775510204082,
          1006.4999999999999
        ],
        [
          1427.8775510204082,
          1013.4999999999999
        ],
        [
          1341.8775510204082,
          995.4999999999999
        ],
        [
          1201.8775510204082,
          1009.4999999999999
        ],
        [
          1134.8775510204082,
          1000.4999999999999
        ],
        [
          1043.8775510204082,
          1037.5
        ],
        [
          922.8775510204082,
          1022.5
        ],
        [
          864.8775510204082,
          985.5000000000002
        ],
        [
          801.8775510204082,
          980.5000000000002
        ],
        [
          758.8775510204082,
          994.4999999999999
        ],
        [
          705.8775510204082,
          987.5000000000002
        ],
        [
          692.8775510204082,
          1011.4999999999999
        ],
        [
          663.8775510204082,
          1019.5
        ],
        [
          641.8775510204082,
          1015.4999999999999
        ],
        [
          618.8775510204082,
          986.5000000000002
        ],
        [
          590.8775510204082,
          998.4999999999999
        ],
        [
          512.8775510204082,
          999.4999999999999
        ],
        [
          490.8775510204082,
          1023.5
        ],
        [
          392.8775510204082,
          1023.5
        ],
        [
          341.8775510204082,
          1007.4999999999999
        ],
        [
          351.8775510204082,
          992.4999999999999
        ],
        [
          318.8775510204082,
          985.5000000000002
        ],
        [
          298.8775510204082,
          996.4999999999999
        ],
        [
          287.8775510204082,
          973.5000000000002
        ],
        [
          213.3775510204082,
          966.0000000000001
        ],
        [
          149.63265306122435,
          977.3061224489796
        ],
        [
          159.83673469387742,
          648.734693877551
        ],
        [
          223.8775510204082,
          653.5
        ],
        [
          343.8775510204082,
          651.5
        ],
        [
          402.8775510204082,
          670.5
        ],
        [
          530.8775510204082,
          670.5
        ],
        [
          603.8775510204082,
          643.5
        ],
        [
          672.8775510204082,
          641.5
        ],
        [
          709.8775510204082,
          654.5
        ],
        [
          811.8775510204082,
          640.5
        ],
        [
          836.8775510204082,
          650.5
        ],
        [
          907.8775510204082,
          630.5
        ],
        [
          937.3775510204082,
          695.0
        ],
        [
          956.8775510204082,
          698.5
        ],
        [
          1024.8775510204082,
          679.5
        ],
        [
          1101.8775510204082,
          681.5
        ],
        [
          1200.8775510204082,
          654.5
        ],
        [
          1262.8775510204082,
          668.5
        ],
        [
          1356.8775510204082,
          667.5
        ],
        [
          1367.8775510204082,
          691.5
        ],
        [
          1407.8775510204082,
          709.5
        ],
        [
          1463.8775510204082,
          695.5
        ],
        [
          1516.8775510204082,
          663.5
        ],
        [
          1623.8775510204082,
          667.5
        ],
        [
          1667.8775510204082,
          702.5
        ],
        [
          1730.8775510204082,
          682.5
        ],
        [
          1827.8775510204082,
          695.5
        ],
        [
          1931.8775510204082,
          656.5
        ],
        [
          1957.8775510204082,
          658.5
        ],
        [
          1997.8775510204082,
          692.5
        ],
        [
          2165.877551020408,
          667.5
        ],
        [
          2200.877551020408,
          685.5
        ],
        [
          2274.877551020408,
          687.5
        ],
        [
          2341.469387755102,
          689.5510204081633
        ],
        [
          2343.5102040816328,
          960.9795918367347
        ],
        [
          2253.877551020408,
          1008.4999999999999
        ],
        [
          2178.877551020408,
          1023.5
        ],
        [
          2126.877551020408,
          999.4999999999999
        ],
        [
          2063.877551020408,
          1002.4999999999999
        ],
        [
          1968.8775510204082,
          1046.5
        ],
        [
          1844.8775510204082,
          1013.4999999999999
        ]
      ],
      "group_id": null,
      "description": "",
      "shape_type": "polygon",
      "flags": {},
      "mask": null
    },
    {
      "label": "scratch",
      "points": [
        [
          145.0,
          1006.5
        ],
        [
          134.0,
          1004.5
        ],
        [
          125.0,
          993.5
        ],
        [
          102.0,
          984.5
        ],
        [
          92.0,
          981.5
        ],
        [
          72.0,
          982.5
        ],
        [
          49.0,
          974.5
        ],
        [
          30.0,
          976.5
        ],
        [
          15.0,
          984.5
        ],
        [
          0.5,
          986.0
        ],
        [
          1.0,
          641.5
        ],
        [
          18.0,
          637.5
        ],
        [
          38.0,
          637.5
        ],
        [
          51.0,
          641.5
        ],
        [
          69.0,
          636.5
        ],
        [
          83.0,
          636.5
        ],
        [
          94.0,
          643.5
        ],
        [
          102.0,
          645.5
        ],
        [
          124.0,
          634.5
        ],
        [
          134.0,
          621.5
        ],
        [
          143.0,
          617.5
        ],
        [
          157.0,
          614.5
        ],
        [
          166.0,
          617.5
        ],
        [
          169.5,
          623.0
        ],
        [
          178.5,
          651.0
        ],
        [
          179.5,
          809.0
        ],
        [
          177.5,
          864.0
        ],
        [
          169.5,
          974.0
        ],
        [
          166.5,
          985.0
        ],
        [
          157.5,
          997.0
        ]
      ],
      "group_id": null,
      "description": "",
      "shape_type": "polygon",
      "flags": {},
      "mask": null
    },
    {
      "label": "mark",
      "points": [
        [
          2326.3333333333335,
          3.6666666666666288
        ],
        [
          2267.896502498216,
          1823.0
        ],
        [
          1451.3333333333335,
          1823.0
        ],
        [
          1532.061346795383,
          0.0
        ]
      ],
      "group_id": null,
      "description": "",
      "shape_type": "polygon",
      "flags": {},
      "mask": null
    },
    {
      "label": "mark",
      "points": [
        [
          209.66666666666674,
          12.0
        ],
        [
          143.41056910569114,
          1823.0
        ],
        [
          0.0,
          1823.0
        ],
        [
          0.0,
          0.0
        ]
      ],
      "group_id": null,
      "description": "",
      "shape_type": "polygon",
      "flags": {},
      "mask": null
    }
  ],
  "imagePath": "2 (8).tif",
  "imageData": null,
  "imageHeight": 1824,
  "imageWidth": 2736
}